{"name":"高精度","permalink":"http://lzy-foenix.github.io/categories/高精度/","url":"\\async\\categories\\高精度.json","count":2,"_total":2,"_totalPage":1,"_page":1,"posts":[{"tags":[{"name":"高精度","permalink":"http://lzy-foenix.github.io/tags/高精度/","url":"\\async\\tags\\高精度.json","count":1}],"categories":[{"name":"高精度","permalink":"http://lzy-foenix.github.io/categories/高精度/","url":"\\async\\categories\\高精度.json","count":2}],"url":"\\async\\posts\\2015\\03\\13\\BZOJ-2656[ZJOI2012]数列.json","date":1426251725000,"path":{"year":2015,"month":3,"day":13,"name":"BZOJ-2656[ZJOI2012]数列"},"title":"BZOJ-2656[Zjoi2012]数列","permalink":"http://lzy-foenix.github.io/2015/03/13/BZOJ-2656[ZJOI2012]数列/","content":"<hr>"},{"tags":[{"name":"高精度封装","permalink":"http://lzy-foenix.github.io/tags/高精度封装/","url":"\\async\\tags\\高精度封装.json","count":1}],"categories":[{"name":"高精度","permalink":"http://lzy-foenix.github.io/categories/高精度/","url":"\\async\\categories\\高精度.json","count":2}],"url":"\\async\\posts\\2015\\03\\19\\高精度封装.json","date":1426761011000,"path":{"year":2015,"month":3,"day":19,"name":"高精度封装"},"title":"高精度封装","permalink":"http://lzy-foenix.github.io/2015/03/19/高精度封装/","content":"<hr>"}]}