{"name":"复习计划","permalink":"http://lzy-foenix.github.io/tags/复习计划/","url":"\\async\\tags\\复习计划.json","count":3,"_total":3,"_totalPage":1,"_page":1,"posts":[{"tags":[{"name":"复习计划","permalink":"http://lzy-foenix.github.io/tags/复习计划/","url":"\\async\\tags\\复习计划.json","count":3}],"categories":[{"name":"杂文","permalink":"http://lzy-foenix.github.io/categories/杂文/","url":"\\async\\categories\\杂文.json","count":13}],"url":"\\async\\posts\\2015\\03\\18\\蒟蒻省选前的复习计划.json","date":1426669952000,"path":{"year":2015,"month":3,"day":18,"name":"蒟蒻省选前的复习计划"},"title":"蒟蒻省选前的复习计划","permalink":"http://lzy-foenix.github.io/2015/03/18/蒟蒻省选前的复习计划/","content":"<hr>"},{"tags":[{"name":"复习计划","permalink":"http://lzy-foenix.github.io/tags/复习计划/","url":"\\async\\tags\\复习计划.json","count":3}],"categories":[{"name":"杂文","permalink":"http://lzy-foenix.github.io/categories/杂文/","url":"\\async\\categories\\杂文.json","count":13}],"url":"\\async\\posts\\2015\\04\\11\\省选倒计时-复习计划.json","date":1428754937000,"path":{"year":2015,"month":4,"day":11,"name":"省选倒计时-复习计划"},"title":"省选倒计时_复习计划","permalink":"http://lzy-foenix.github.io/2015/04/11/省选倒计时-复习计划/","content":"<hr>"},{"tags":[{"name":"复习计划","permalink":"http://lzy-foenix.github.io/tags/复习计划/","url":"\\async\\tags\\复习计划.json","count":3}],"categories":[{"name":"杂文","permalink":"http://lzy-foenix.github.io/categories/杂文/","url":"\\async\\categories\\杂文.json","count":13}],"url":"\\async\\posts\\2015\\04\\11\\目前掌握的东西-太弱了.json","date":1428754549000,"path":{"year":2015,"month":4,"day":11,"name":"目前掌握的东西-太弱了"},"title":"目前掌握的东西...太弱了","permalink":"http://lzy-foenix.github.io/2015/04/11/目前掌握的东西-太弱了/","content":"<hr>"}]}